{
  "Name": "Firefly",
  "Desc": "A member of the Stellaron Hunters, wearing a set of mechanized armor known as \"SAM.\" Her character is marked by unwavering loyalty and determination.\\nEngineered as a weapon against the Swarm, she experiences accelerated growth, but a tragically shortened lifespan.\\nShe joined the Stellaron Hunters in search of a way to defy her fated demise.",
  "CharaInfo": {
    "Camp": null,
    "VA": {
      "Chinese": null,
      "Japanese": null,
      "Korean": null,
      "English": null
    },
    "Stories": {
      "0": null,
      "1": null,
      "2": null,
      "3": null,
      "4": null
    },
    "Voicelines": []
  },
  "Rarity": "CombatPowerAvatarRarityType5",
  "AvatarVOTag": "sam",
  "SPNeed": 240,
  "BaseType": "Warrior",
  "DamageType": "Fire",
  "Ranks": {
    "1": {
      "Id": 131001,
      "Name": "In Reddened Chrysalis, I Once Rest",
      "Desc": "When using the Enhanced Skill, ignores <unbreak>#1[i]%</unbreak> of the target's DEF. And the Enhanced Skill does not consume Skill Points.",
      "ParamList": [
        0.1500000001396984
      ]
    },
    "2": {
      "Id": 131002,
      "Name": "From Shattered Sky, I Free Fall",
      "Desc": "When using the Enhanced Basic ATK or the Enhanced Skill in Complete Combustion state to defeat an enemy target or cause them to be Weakness Broken, SAM immediately gains 1 extra turn. This effect can trigger again after <unbreak>#2[i]</unbreak> turn(s).",
      "ParamList": [
        1,
        1
      ]
    },
    "3": {
      "Id": 131003,
      "Name": "Amidst Silenced Stars, I Deep Sleep",
      "Desc": "Skill Lv. +2, up to a maximum of Lv. <unbreak>15</unbreak>.\\nBasic ATK Lv. +1, up to a maximum of Lv. <unbreak>10</unbreak>.",
      "ParamList": []
    },
    "4": {
      "Id": 131004,
      "Name": "Upon Lighted Fyrefly, I Soon Gaze",
      "Desc": "When in the Complete Combustion state, increases SAM's Effect RES by <unbreak>#1[i]%</unbreak>.",
      "ParamList": [
        0.5000000004656613
      ]
    },
    "5": {
      "Id": 131005,
      "Name": "From Undreamt Night, I Thence Shine",
      "Desc": "Ultimate Lv. +2, up to a maximum of Lv. <unbreak>15</unbreak>.\\nTalent Lv. +2, up to a maximum of Lv. <unbreak>15</unbreak>.",
      "ParamList": []
    },
    "6": {
      "Id": 131006,
      "Name": "In Finalized Morrow, I Full Bloom",
      "Desc": "While in Complete Combustion, increases SAM's Fire RES PEN by <unbreak>#1[i]%</unbreak>. When using the Enhanced Basic ATK or Enhanced Skill, increases the Weakness Break efficiency by <unbreak>#2[i]%</unbreak>.",
      "ParamList": [
        0.20000000018626451,
        0.5000000004656613
      ]
    }
  },
  "Skills": {
    "131001": {
      "Name": "Order: Flare Propulsion",
      "Desc": "Deals Fire DMG equal to <color=#f29e38ff><unbreak>#1[i]%</unbreak></color> of SAM's ATK to a single target enemy.",
      "Type": "Normal",
      "Tag": "SingleAttack",
      "SPBase": 20,
      "ShowStanceList": [
        30,
        0,
        0
      ],
      "SkillComboValueDelta": null,
      "Level": {
        "1": {
          "Level": 1,
          "ParamList": [
            0.5000000004656613
          ]
        },
        "2": {
          "Level": 2,
          "ParamList": [
            0.6000000005587935
          ]
        },
        "3": {
          "Level": 3,
          "ParamList": [
            0.7000000006519258
          ]
        },
        "4": {
          "Level": 4,
          "ParamList": [
            0.8000000007450581
          ]
        },
        "5": {
          "Level": 5,
          "ParamList": [
            0.9000000008381903
          ]
        },
        "6": {
          "Level": 6,
          "ParamList": [
            1
          ]
        },
        "7": {
          "Level": 7,
          "ParamList": [
            1.1000000000931323
          ]
        },
        "8": {
          "Level": 8,
          "ParamList": [
            1.2000000001862645
          ]
        },
        "9": {
          "Level": 9,
          "ParamList": [
            1.3000000002793968
          ]
        }
      }
    },
    "131002": {
      "Name": "Order: Aerial Bombardment",
      "Desc": "Consumes SAM's HP equal to <unbreak>#2[i]%</unbreak> of SAM's Max HP and regenerates a fixed amount of Energy equal to <unbreak>#3[i]%</unbreak> of SAM's Max Energy. Deals Fire DMG equal to <color=#f29e38ff><unbreak>#1[i]%</unbreak></color> of SAM's ATK to a single target enemy. If the current HP is not sufficient, then SAM's HP is reduced to 1 when using this Skill. Causes character's next <u>Action to be Advanced</u> by <unbreak>#4[i]%</unbreak>.",
      "Type": "BPSkill",
      "Tag": "SingleAttack",
      "SPBase": null,
      "ShowStanceList": [
        60,
        0,
        0
      ],
      "SkillComboValueDelta": null,
      "Level": {
        "1": {
          "Level": 1,
          "ParamList": [
            1,
            0.40000000037252903,
            0.6000000005587935,
            0.25000000023283064
          ]
        },
        "2": {
          "Level": 2,
          "ParamList": [
            1.1000000000931323,
            0.40000000037252903,
            0.6000000005587935,
            0.25000000023283064
          ]
        },
        "3": {
          "Level": 3,
          "ParamList": [
            1.2000000001862645,
            0.40000000037252903,
            0.6000000005587935,
            0.25000000023283064
          ]
        },
        "4": {
          "Level": 4,
          "ParamList": [
            1.3000000002793968,
            0.40000000037252903,
            0.6000000005587935,
            0.25000000023283064
          ]
        },
        "5": {
          "Level": 5,
          "ParamList": [
            1.400000000372529,
            0.40000000037252903,
            0.6000000005587935,
            0.25000000023283064
          ]
        },
        "6": {
          "Level": 6,
          "ParamList": [
            1.5000000004656613,
            0.40000000037252903,
            0.6000000005587935,
            0.25000000023283064
          ]
        },
        "7": {
          "Level": 7,
          "ParamList": [
            1.6250000002328306,
            0.40000000037252903,
            0.6000000005587935,
            0.25000000023283064
          ]
        },
        "8": {
          "Level": 8,
          "ParamList": [
            1.750000000698492,
            0.40000000037252903,
            0.6000000005587935,
            0.25000000023283064
          ]
        },
        "9": {
          "Level": 9,
          "ParamList": [
            1.8750000004656613,
            0.40000000037252903,
            0.6000000005587935,
            0.25000000023283064
          ]
        },
        "10": {
          "Level": 10,
          "ParamList": [
            2,
            0.40000000037252903,
            0.6000000005587935,
            0.25000000023283064
          ]
        },
        "11": {
          "Level": 11,
          "ParamList": [
            2.1000000000931323,
            0.40000000037252903,
            0.6000000005587935,
            0.25000000023283064
          ]
        },
        "12": {
          "Level": 12,
          "ParamList": [
            2.2000000001862645,
            0.40000000037252903,
            0.6000000005587935,
            0.25000000023283064
          ]
        },
        "13": {
          "Level": 13,
          "ParamList": [
            2.3000000002793968,
            0.40000000037252903,
            0.6000000005587935,
            0.25000000023283064
          ]
        },
        "14": {
          "Level": 14,
          "ParamList": [
            2.400000000372529,
            0.40000000037252903,
            0.6000000005587935,
            0.25000000023283064
          ]
        },
        "15": {
          "Level": 15,
          "ParamList": [
            2.5000000004656613,
            0.40000000037252903,
            0.6000000005587935,
            0.25000000023283064
          ]
        }
      }
    },
    "131003": {
      "Name": "Fyrefly Type-IV: Complete Combustion",
      "Desc": "Upon entering the Complete Combustion state, Advances SAM's Action by <unbreak>100%</unbreak> and gains Enhanced Basic ATK and Enhanced Skill. While in Complete Combustion, increases SPD by <color=#f29e38ff><unbreak>#3[i]</unbreak></color>, and when using the Enhanced Basic ATK or Enhanced Skill, increases SAM's Weakness Break efficiency by <unbreak>#2[i]%</unbreak>, increases the Break DMG enemy targets receive by <color=#f29e38ff><unbreak>#1[f1]%</unbreak></color>, lasting until the current attack ends.\\nA countdown timer for the Complete Combustion state appears on the Action Order. When the countdown turn starts, SAM exits the Complete Combustion state. The countdown has a fixed SPD of <unbreak>#4[i]</unbreak>.\\nSAM cannot use Ultimate while in Complete Combustion.",
      "Type": "Ultra",
      "Tag": "Enhance",
      "SPBase": 5,
      "ShowStanceList": [
        0,
        0,
        0
      ],
      "SkillComboValueDelta": null,
      "Level": {
        "1": {
          "Level": 1,
          "ParamList": [
            0.10000000009313226,
            0.5000000004656613,
            30,
            70
          ]
        },
        "2": {
          "Level": 2,
          "ParamList": [
            0.11000000010244548,
            0.5000000004656613,
            33,
            70
          ]
        },
        "3": {
          "Level": 3,
          "ParamList": [
            0.12000000011175871,
            0.5000000004656613,
            36,
            70
          ]
        },
        "4": {
          "Level": 4,
          "ParamList": [
            0.13000000012107193,
            0.5000000004656613,
            39,
            70
          ]
        },
        "5": {
          "Level": 5,
          "ParamList": [
            0.14000000013038516,
            0.5000000004656613,
            42,
            70
          ]
        },
        "6": {
          "Level": 6,
          "ParamList": [
            0.1500000001396984,
            0.5000000004656613,
            45,
            70
          ]
        },
        "7": {
          "Level": 7,
          "ParamList": [
            0.1625000003259629,
            0.5000000004656613,
            48.75000000069849,
            70
          ]
        },
        "8": {
          "Level": 8,
          "ParamList": [
            0.17499999981373549,
            0.5000000004656613,
            52.50000000046566,
            70
          ]
        },
        "9": {
          "Level": 9,
          "ParamList": [
            0.1875,
            0.5000000004656613,
            56.25000000023283,
            70
          ]
        },
        "10": {
          "Level": 10,
          "ParamList": [
            0.20000000018626451,
            0.5000000004656613,
            60,
            70
          ]
        },
        "11": {
          "Level": 11,
          "ParamList": [
            0.21000000019557774,
            0.5000000004656613,
            63,
            70
          ]
        },
        "12": {
          "Level": 12,
          "ParamList": [
            0.22000000020489097,
            0.5000000004656613,
            66,
            70
          ]
        },
        "13": {
          "Level": 13,
          "ParamList": [
            0.2300000002142042,
            0.5000000004656613,
            69,
            70
          ]
        },
        "14": {
          "Level": 14,
          "ParamList": [
            0.24000000022351742,
            0.5000000004656613,
            72,
            70
          ]
        },
        "15": {
          "Level": 15,
          "ParamList": [
            0.25000000023283064,
            0.5000000004656613,
            75,
            70
          ]
        }
      }
    },
    "131004": {
      "Name": "Chrysalid Pyronexus",
      "Desc": "The lower the HP, the lower the DMG received. When HP is <unbreak>#3[i]%</unbreak> or lower, the DMG Reduction reaches its maximum effect, reducing up to a maximum of <color=#f29e38ff><unbreak>#1[i]%</unbreak></color>. During the Complete Combustion, the DMG Reduction remains at its maximum effect, and the Effect RES increases by <color=#f29e38ff><unbreak>#4[i]%</unbreak></color>.\\nIf Energy is lower than <unbreak>#2[i]%</unbreak> when the battle starts, regenerates Energy to <unbreak>#2[i]%</unbreak>. Once Energy is regenerated to its maximum, dispels all <u>debuffs</u> on SAM.",
      "Type": null,
      "Tag": "Defence",
      "SPBase": null,
      "ShowStanceList": [
        0,
        0,
        0
      ],
      "SkillComboValueDelta": null,
      "Level": {
        "1": {
          "Level": 1,
          "ParamList": [
            0.20000000018626451,
            0.5000000004656613,
            0.20000000018626451,
            0.10000000009313226
          ]
        },
        "2": {
          "Level": 2,
          "ParamList": [
            0.22000000020489097,
            0.5000000004656613,
            0.20000000018626451,
            0.12000000011175871
          ]
        },
        "3": {
          "Level": 3,
          "ParamList": [
            0.24000000022351742,
            0.5000000004656613,
            0.20000000018626451,
            0.14000000013038516
          ]
        },
        "4": {
          "Level": 4,
          "ParamList": [
            0.26000000024214387,
            0.5000000004656613,
            0.20000000018626451,
            0.1600000001490116
          ]
        },
        "5": {
          "Level": 5,
          "ParamList": [
            0.2800000002607703,
            0.5000000004656613,
            0.20000000018626451,
            0.18000000016763806
          ]
        },
        "6": {
          "Level": 6,
          "ParamList": [
            0.3000000002793968,
            0.5000000004656613,
            0.20000000018626451,
            0.20000000018626451
          ]
        },
        "7": {
          "Level": 7,
          "ParamList": [
            0.32499999995343387,
            0.5000000004656613,
            0.20000000018626451,
            0.2249999998603016
          ]
        },
        "8": {
          "Level": 8,
          "ParamList": [
            0.3500000003259629,
            0.5000000004656613,
            0.20000000018626451,
            0.25000000023283064
          ]
        },
        "9": {
          "Level": 9,
          "ParamList": [
            0.375,
            0.5000000004656613,
            0.20000000018626451,
            0.27499999990686774
          ]
        },
        "10": {
          "Level": 10,
          "ParamList": [
            0.40000000037252903,
            0.5000000004656613,
            0.20000000018626451,
            0.3000000002793968
          ]
        },
        "11": {
          "Level": 11,
          "ParamList": [
            0.4200000003911555,
            0.5000000004656613,
            0.20000000018626451,
            0.3200000002980232
          ]
        },
        "12": {
          "Level": 12,
          "ParamList": [
            0.44000000040978193,
            0.5000000004656613,
            0.20000000018626451,
            0.3400000003166497
          ]
        },
        "13": {
          "Level": 13,
          "ParamList": [
            0.4600000004284084,
            0.5000000004656613,
            0.20000000018626451,
            0.3600000003352761
          ]
        },
        "14": {
          "Level": 14,
          "ParamList": [
            0.48000000044703484,
            0.5000000004656613,
            0.20000000018626451,
            0.3800000003539026
          ]
        },
        "15": {
          "Level": 15,
          "ParamList": [
            0.5000000004656613,
            0.5000000004656613,
            0.20000000018626451,
            0.40000000037252903
          ]
        }
      }
    },
    "131006": {
      "Name": "Attack",
      "Desc": "Attacks an enemy, and when the battle starts, reduces their Toughness of the corresponding Type.",
      "Type": "MazeNormal",
      "Tag": "MazeAttack",
      "SPBase": null,
      "ShowStanceList": [
        30,
        0,
        0
      ],
      "SkillComboValueDelta": null,
      "Level": {
        "1": {
          "Level": 1,
          "ParamList": []
        }
      }
    },
    "131007": {
      "Name": "Δ Order: Meteoric Incineration",
      "Desc": "Leaps into the air and moves without restrictions for <unbreak>#1[i]</unbreak> seconds, which can be ended early by launching a Plunging Attack. When this duration ends, SAM descends and immediately attacks all enemies within a set area. At the start of each wave, applies a Fire Weakness to all enemies, lasting for <unbreak>#3[i]</unbreak> turn(s). Then, deals Fire DMG equal to <unbreak>#2[i]%</unbreak> of SAM's ATK to all enemies.",
      "Type": "Maze",
      "Tag": "MazeAttack",
      "SPBase": null,
      "ShowStanceList": [
        60,
        0,
        0
      ],
      "SkillComboValueDelta": null,
      "Level": {
        "1": {
          "Level": 1,
          "ParamList": [
            5,
            2,
            2
          ]
        }
      }
    },
    "131008": {
      "Name": "Fyrefly Type-IV: Pyrogenic Decimation",
      "Desc": "Restores HP by an amount equal to <unbreak>#2[i]%</unbreak> of this unit's Max HP. Deals Fire DMG equal to <color=#f29e38ff><unbreak>#1[i]%</unbreak></color> of SAM's ATK to a single target enemy.",
      "Type": "Normal",
      "Tag": "SingleAttack",
      "SPBase": null,
      "ShowStanceList": [
        45,
        0,
        0
      ],
      "SkillComboValueDelta": null,
      "Level": {
        "1": {
          "Level": 1,
          "ParamList": [
            1,
            0.20000000018626451
          ]
        },
        "2": {
          "Level": 2,
          "ParamList": [
            1.2000000001862645,
            0.20000000018626451
          ]
        },
        "3": {
          "Level": 3,
          "ParamList": [
            1.400000000372529,
            0.20000000018626451
          ]
        },
        "4": {
          "Level": 4,
          "ParamList": [
            1.6000000005587935,
            0.20000000018626451
          ]
        },
        "5": {
          "Level": 5,
          "ParamList": [
            1.800000000745058,
            0.20000000018626451
          ]
        },
        "6": {
          "Level": 6,
          "ParamList": [
            2,
            0.20000000018626451
          ]
        },
        "7": {
          "Level": 7,
          "ParamList": [
            2.2000000001862645,
            0.20000000018626451
          ]
        },
        "8": {
          "Level": 8,
          "ParamList": [
            2.400000000372529,
            0.20000000018626451
          ]
        },
        "9": {
          "Level": 9,
          "ParamList": [
            2.6000000005587935,
            0.20000000018626451
          ]
        }
      }
    },
    "131009": {
      "Name": "Fyrefly Type-IV: Deathstar Overload",
      "Desc": "Restores HP by <unbreak>#3[i]%</unbreak> of this unit's Max HP. Applies Fire Weakness to a single enemy, lasting for <unbreak>#4[i]</unbreak> turn(s). Deals Fire DMG equal to <unbreak>#5[f1]</unbreak> × Break Effect + <color=#f29e38ff><unbreak>#1[f1]%</unbreak></color> of SAM's ATK to the target enemy. At the same time, deals Fire DMG equal to <unbreak>#6[f2]</unbreak> × Break Effect + <color=#f29e38ff><unbreak>#2[f1]%</unbreak></color> of SAM's ATK to adjacent enemies. A maximum of <unbreak>#7[i]%</unbreak> Break Effect is calculated.",
      "Type": "BPSkill",
      "Tag": "Blast",
      "SPBase": null,
      "ShowStanceList": [
        90,
        0,
        45
      ],
      "SkillComboValueDelta": null,
      "Level": {
        "1": {
          "Level": 1,
          "ParamList": [
            1,
            0.5000000004656613,
            0.3500000003259629,
            2,
            0.20000000018626451,
            0.10000000009313226,
            3.6000000005587935
          ]
        },
        "2": {
          "Level": 2,
          "ParamList": [
            1.1000000000931323,
            0.5500000005122274,
            0.3500000003259629,
            2,
            0.20000000018626451,
            0.10000000009313226,
            3.6000000005587935
          ]
        },
        "3": {
          "Level": 3,
          "ParamList": [
            1.2000000001862645,
            0.6000000005587935,
            0.3500000003259629,
            2,
            0.20000000018626451,
            0.10000000009313226,
            3.6000000005587935
          ]
        },
        "4": {
          "Level": 4,
          "ParamList": [
            1.3000000002793968,
            0.6500000006053597,
            0.3500000003259629,
            2,
            0.20000000018626451,
            0.10000000009313226,
            3.6000000005587935
          ]
        },
        "5": {
          "Level": 5,
          "ParamList": [
            1.400000000372529,
            0.7000000006519258,
            0.3500000003259629,
            2,
            0.20000000018626451,
            0.10000000009313226,
            3.6000000005587935
          ]
        },
        "6": {
          "Level": 6,
          "ParamList": [
            1.5000000004656613,
            0.7500000006984919,
            0.3500000003259629,
            2,
            0.20000000018626451,
            0.10000000009313226,
            3.6000000005587935
          ]
        },
        "7": {
          "Level": 7,
          "ParamList": [
            1.6250000002328306,
            0.8125000009313226,
            0.3500000003259629,
            2,
            0.20000000018626451,
            0.10000000009313226,
            3.6000000005587935
          ]
        },
        "8": {
          "Level": 8,
          "ParamList": [
            1.750000000698492,
            0.8750000004656613,
            0.3500000003259629,
            2,
            0.20000000018626451,
            0.10000000009313226,
            3.6000000005587935
          ]
        },
        "9": {
          "Level": 9,
          "ParamList": [
            1.8750000004656613,
            0.9375000006984919,
            0.3500000003259629,
            2,
            0.20000000018626451,
            0.10000000009313226,
            3.6000000005587935
          ]
        },
        "10": {
          "Level": 10,
          "ParamList": [
            2,
            1,
            0.3500000003259629,
            2,
            0.20000000018626451,
            0.10000000009313226,
            3.6000000005587935
          ]
        },
        "11": {
          "Level": 11,
          "ParamList": [
            2.1000000000931323,
            1.0500000000465661,
            0.3500000003259629,
            2,
            0.20000000018626451,
            0.10000000009313226,
            3.6000000005587935
          ]
        },
        "12": {
          "Level": 12,
          "ParamList": [
            2.2000000001862645,
            1.1000000000931323,
            0.3500000003259629,
            2,
            0.20000000018626451,
            0.10000000009313226,
            3.6000000005587935
          ]
        },
        "13": {
          "Level": 13,
          "ParamList": [
            2.3000000002793968,
            1.1500000001396984,
            0.3500000003259629,
            2,
            0.20000000018626451,
            0.10000000009313226,
            3.6000000005587935
          ]
        },
        "14": {
          "Level": 14,
          "ParamList": [
            2.400000000372529,
            1.2000000001862645,
            0.3500000003259629,
            2,
            0.20000000018626451,
            0.10000000009313226,
            3.6000000005587935
          ]
        },
        "15": {
          "Level": 15,
          "ParamList": [
            2.5000000004656613,
            1.2500000002328306,
            0.3500000003259629,
            2,
            0.20000000018626451,
            0.10000000009313226,
            3.6000000005587935
          ]
        }
      }
    }
  },
  "SkillTrees": {
    "Point01": {
      "1": {
        "Anchor": "Point01",
        "AvatarPromotionLimit": null,
        "AvatarLevelLimit": null,
        "DefaultUnlock": true,
        "Icon": "SkillIcon_1310_Normal.png",
        "LevelUpSkillID": [
          131001,
          131008
        ],
        "MaterialList": [],
        "MaxLevel": 6,
        "ParamList": [],
        "PointID": 1310001,
        "PointName": null,
        "PointDesc": null,
        "PointTriggerKey": 515615555,
        "PointType": 2,
        "PrePoint": [],
        "StatusAddList": []
      },
      "2": {
        "Anchor": "Point01",
        "AvatarPromotionLimit": 2,
        "AvatarLevelLimit": null,
        "DefaultUnlock": false,
        "Icon": "SkillIcon_1310_Normal.png",
        "LevelUpSkillID": [
          131001,
          131008
        ],
        "MaterialList": [
          {
            "$type": "ItemConfigRow",
            "ItemID": 2,
            "ItemNum": 5000
          },
          {
            "$type": "ItemConfigRow",
            "ItemID": 110181,
            "ItemNum": 3
          },
          {
            "$type": "ItemConfigRow",
            "ItemID": 114011,
            "ItemNum": 6
          }
        ],
        "MaxLevel": 6,
        "ParamList": [],
        "PointID": 1310001,
        "PointName": null,
        "PointDesc": null,
        "PointTriggerKey": 515615555,
        "PointType": 2,
        "PrePoint": [],
        "StatusAddList": []
      },
      "3": {
        "Anchor": "Point01",
        "AvatarPromotionLimit": 3,
        "AvatarLevelLimit": null,
        "DefaultUnlock": false,
        "Icon": "SkillIcon_1310_Normal.png",
        "LevelUpSkillID": [
          131001,
          131008
        ],
        "MaterialList": [
          {
            "$type": "ItemConfigRow",
            "ItemID": 2,
            "ItemNum": 10000
          },
          {
            "$type": "ItemConfigRow",
            "ItemID": 110182,
            "ItemNum": 3
          },
          {
            "$type": "ItemConfigRow",
            "ItemID": 114012,
            "ItemNum": 3
          }
        ],
        "MaxLevel": 6,
        "ParamList": [],
        "PointID": 1310001,
        "PointName": null,
        "PointDesc": null,
        "PointTriggerKey": 515615555,
        "PointType": 2,
        "PrePoint": [],
        "StatusAddList": []
      },
      "4": {
        "Anchor": "Point01",
        "AvatarPromotionLimit": 4,
        "AvatarLevelLimit": null,
        "DefaultUnlock": false,
        "Icon": "SkillIcon_1310_Normal.png",
        "LevelUpSkillID": [
          131001,
          131008
        ],
        "MaterialList": [
          {
            "$type": "ItemConfigRow",
            "ItemID": 2,
            "ItemNum": 20000
          },
          {
            "$type": "ItemConfigRow",
            "ItemID": 110182,
            "ItemNum": 5
          },
          {
            "$type": "ItemConfigRow",
            "ItemID": 114012,
            "ItemNum": 4
          }
        ],
        "MaxLevel": 6,
        "ParamList": [],
        "PointID": 1310001,
        "PointName": null,
        "PointDesc": null,
        "PointTriggerKey": 515615555,
        "PointType": 2,
        "PrePoint": [],
        "StatusAddList": []
      },
      "5": {
        "Anchor": "Point01",
        "AvatarPromotionLimit": 5,
        "AvatarLevelLimit": null,
        "DefaultUnlock": false,
        "Icon": "SkillIcon_1310_Normal.png",
        "LevelUpSkillID": [
          131001,
          131008
        ],
        "MaterialList": [
          {
            "$type": "ItemConfigRow",
            "ItemID": 2,
            "ItemNum": 45000
          },
          {
            "$type": "ItemConfigRow",
            "ItemID": 110183,
            "ItemNum": 3
          },
          {
            "$type": "ItemConfigRow",
            "ItemID": 114013,
            "ItemNum": 3
          }
        ],
        "MaxLevel": 6,
        "ParamList": [],
        "PointID": 1310001,
        "PointName": null,
        "PointDesc": null,
        "PointTriggerKey": 515615555,
        "PointType": 2,
        "PrePoint": [],
        "StatusAddList": []
      },
      "6": {
        "Anchor": "Point01",
        "AvatarPromotionLimit": 6,
        "AvatarLevelLimit": null,
        "DefaultUnlock": false,
        "Icon": "SkillIcon_1310_Normal.png",
        "LevelUpSkillID": [
          131001,
          131008
        ],
        "MaterialList": [
          {
            "$type": "ItemConfigRow",
            "ItemID": 2,
            "ItemNum": 160000
          },
          {
            "$type": "ItemConfigRow",
            "ItemID": 110183,
            "ItemNum": 8
          },
          {
            "$type": "ItemConfigRow",
            "ItemID": 114013,
            "ItemNum": 4
          }
        ],
        "MaxLevel": 6,
        "ParamList": [],
        "PointID": 1310001,
        "PointName": null,
        "PointDesc": null,
        "PointTriggerKey": 515615555,
        "PointType": 2,
        "PrePoint": [],
        "StatusAddList": []
      }
    },
    "Point02": {
      "1": {
        "Anchor": "Point02",
        "AvatarPromotionLimit": null,
        "AvatarLevelLimit": null,
        "DefaultUnlock": true,
        "Icon": "SkillIcon_1310_BP.png",
        "LevelUpSkillID": [
          131002,
          131009
        ],
        "MaterialList": [],
        "MaxLevel": 10,
        "ParamList": [],
        "PointID": 1310002,
        "PointName": null,
        "PointDesc": null,
        "PointTriggerKey": -1382908784,
        "PointType": 2,
        "PrePoint": [],
        "StatusAddList": []
      },
      "2": {
        "Anchor": "Point02",
        "AvatarPromotionLimit": 1,
        "AvatarLevelLimit": null,
        "DefaultUnlock": false,
        "Icon": "SkillIcon_1310_BP.png",
        "LevelUpSkillID": [
          131002,
          131009
        ],
        "MaterialList": [
          {
            "$type": "ItemConfigRow",
            "ItemID": 2,
            "ItemNum": 2500
          },
          {
            "$type": "ItemConfigRow",
            "ItemID": 114011,
            "ItemNum": 3
          }
        ],
        "MaxLevel": 10,
        "ParamList": [],
        "PointID": 1310002,
        "PointName": null,
        "PointDesc": null,
        "PointTriggerKey": -1382908784,
        "PointType": 2,
        "PrePoint": [],
        "StatusAddList": []
      },
      "3": {
        "Anchor": "Point02",
        "AvatarPromotionLimit": 2,
        "AvatarLevelLimit": null,
        "DefaultUnlock": false,
        "Icon": "SkillIcon_1310_BP.png",
        "LevelUpSkillID": [
          131002,
          131009
        ],
        "MaterialList": [
          {
            "$type": "ItemConfigRow",
            "ItemID": 2,
            "ItemNum": 5000
          },
          {
            "$type": "ItemConfigRow",
            "ItemID": 110181,
            "ItemNum": 3
          },
          {
            "$type": "ItemConfigRow",
            "ItemID": 114011,
            "ItemNum": 6
          }
        ],
        "MaxLevel": 10,
        "ParamList": [],
        "PointID": 1310002,
        "PointName": null,
        "PointDesc": null,
        "PointTriggerKey": -1382908784,
        "PointType": 2,
        "PrePoint": [],
        "StatusAddList": []
      },
      "4": {
        "Anchor": "Point02",
        "AvatarPromotionLimit": 3,
        "AvatarLevelLimit": null,
        "DefaultUnlock": false,
        "Icon": "SkillIcon_1310_BP.png",
        "LevelUpSkillID": [
          131002,
          131009
        ],
        "MaterialList": [
          {
            "$type": "ItemConfigRow",
            "ItemID": 2,
            "ItemNum": 10000
          },
          {
            "$type": "ItemConfigRow",
            "ItemID": 110182,
            "ItemNum": 3
          },
          {
            "$type": "ItemConfigRow",
            "ItemID": 114012,
            "ItemNum": 3
          }
        ],
        "MaxLevel": 10,
        "ParamList": [],
        "PointID": 1310002,
        "PointName": null,
        "PointDesc": null,
        "PointTriggerKey": -1382908784,
        "PointType": 2,
        "PrePoint": [],
        "StatusAddList": []
      },
      "5": {
        "Anchor": "Point02",
        "AvatarPromotionLimit": 4,
        "AvatarLevelLimit": null,
        "DefaultUnlock": false,
        "Icon": "SkillIcon_1310_BP.png",
        "LevelUpSkillID": [
          131002,
          131009
        ],
        "MaterialList": [
          {
            "$type": "ItemConfigRow",
            "ItemID": 2,
            "ItemNum": 20000
          },
          {
            "$type": "ItemConfigRow",
            "ItemID": 110182,
            "ItemNum": 5
          },
          {
            "$type": "ItemConfigRow",
            "ItemID": 114012,
            "ItemNum": 4
          }
        ],
        "MaxLevel": 10,
        "ParamList": [],
        "PointID": 1310002,
        "PointName": null,
        "PointDesc": null,
        "PointTriggerKey": -1382908784,
        "PointType": 2,
        "PrePoint": [],
        "StatusAddList": []
      },
      "6": {
        "Anchor": "Point02",
        "AvatarPromotionLimit": 4,
        "AvatarLevelLimit": null,
        "DefaultUnlock": false,
        "Icon": "SkillIcon_1310_BP.png",
        "LevelUpSkillID": [
          131002,
          131009
        ],
        "MaterialList": [
          {
            "$type": "ItemConfigRow",
            "ItemID": 2,
            "ItemNum": 30000
          },
          {
            "$type": "ItemConfigRow",
            "ItemID": 110182,
            "ItemNum": 7
          },
          {
            "$type": "ItemConfigRow",
            "ItemID": 114012,
            "ItemNum": 6
          }
        ],
        "MaxLevel": 10,
        "ParamList": [],
        "PointID": 1310002,
        "PointName": null,
        "PointDesc": null,
        "PointTriggerKey": -1382908784,
        "PointType": 2,
        "PrePoint": [],
        "StatusAddList": []
      },
      "7": {
        "Anchor": "Point02",
        "AvatarPromotionLimit": 5,
        "AvatarLevelLimit": null,
        "DefaultUnlock": false,
        "Icon": "SkillIcon_1310_BP.png",
        "LevelUpSkillID": [
          131002,
          131009
        ],
        "MaterialList": [
          {
            "$type": "ItemConfigRow",
            "ItemID": 2,
            "ItemNum": 45000
          },
          {
            "$type": "ItemConfigRow",
            "ItemID": 110183,
            "ItemNum": 3
          },
          {
            "$type": "ItemConfigRow",
            "ItemID": 114013,
            "ItemNum": 3
          }
        ],
        "MaxLevel": 10,
        "ParamList": [],
        "PointID": 1310002,
        "PointName": null,
        "PointDesc": null,
        "PointTriggerKey": -1382908784,
        "PointType": 2,
        "PrePoint": [],
        "StatusAddList": []
      },
      "8": {
        "Anchor": "Point02",
        "AvatarPromotionLimit": 5,
        "AvatarLevelLimit": null,
        "DefaultUnlock": false,
        "Icon": "SkillIcon_1310_BP.png",
        "LevelUpSkillID": [
          131002,
          131009
        ],
        "MaterialList": [
          {
            "$type": "ItemConfigRow",
            "ItemID": 2,
            "ItemNum": 80000
          },
          {
            "$type": "ItemConfigRow",
            "ItemID": 110183,
            "ItemNum": 5
          },
          {
            "$type": "ItemConfigRow",
            "ItemID": 110505,
            "ItemNum": 1
          },
          {
            "$type": "ItemConfigRow",
            "ItemID": 114013,
            "ItemNum": 4
          }
        ],
        "MaxLevel": 10,
        "ParamList": [],
        "PointID": 1310002,
        "PointName": null,
        "PointDesc": null,
        "PointTriggerKey": -1382908784,
        "PointType": 2,
        "PrePoint": [],
        "StatusAddList": []
      },
      "9": {
        "Anchor": "Point02",
        "AvatarPromotionLimit": 6,
        "AvatarLevelLimit": null,
        "DefaultUnlock": false,
        "Icon": "SkillIcon_1310_BP.png",
        "LevelUpSkillID": [
          131002,
          131009
        ],
        "MaterialList": [
          {
            "$type": "ItemConfigRow",
            "ItemID": 2,
            "ItemNum": 160000
          },
          {
            "$type": "ItemConfigRow",
            "ItemID": 110183,
            "ItemNum": 8
          },
          {
            "$type": "ItemConfigRow",
            "ItemID": 241,
            "ItemNum": 1
          },
          {
            "$type": "ItemConfigRow",
            "ItemID": 110505,
            "ItemNum": 1
          }
        ],
        "MaxLevel": 10,
        "ParamList": [],
        "PointID": 1310002,
        "PointName": null,
        "PointDesc": null,
        "PointTriggerKey": -1382908784,
        "PointType": 2,
        "PrePoint": [],
        "StatusAddList": []
      },
      "10": {
        "Anchor": "Point02",
        "AvatarPromotionLimit": 6,
        "AvatarLevelLimit": null,
        "DefaultUnlock": false,
        "Icon": "SkillIcon_1310_BP.png",
        "LevelUpSkillID": [
          131002,
          131009
        ],
        "MaterialList": [
          {
            "$type": "ItemConfigRow",
            "ItemID": 2,
            "ItemNum": 300000
          },
          {
            "$type": "ItemConfigRow",
            "ItemID": 110183,
            "ItemNum": 14
          },
          {
            "$type": "ItemConfigRow",
            "ItemID": 241,
            "ItemNum": 1
          },
          {
            "$type": "ItemConfigRow",
            "ItemID": 110505,
            "ItemNum": 1
          }
        ],
        "MaxLevel": 10,
        "ParamList": [],
        "PointID": 1310002,
        "PointName": null,
        "PointDesc": null,
        "PointTriggerKey": -1382908784,
        "PointType": 2,
        "PrePoint": [],
        "StatusAddList": []
      }
    },
    "Point03": {
      "1": {
        "Anchor": "Point03",
        "AvatarPromotionLimit": null,
        "AvatarLevelLimit": null,
        "DefaultUnlock": true,
        "Icon": "SkillIcon_1310_Ultra.png",
        "LevelUpSkillID": [
          131003
        ],
        "MaterialList": [],
        "MaxLevel": 10,
        "ParamList": [],
        "PointID": 1310003,
        "PointName": null,
        "PointDesc": null,
        "PointTriggerKey": -747226677,
        "PointType": 2,
        "PrePoint": [],
        "StatusAddList": []
      },
      "2": {
        "Anchor": "Point03",
        "AvatarPromotionLimit": 1,
        "AvatarLevelLimit": null,
        "DefaultUnlock": false,
        "Icon": "SkillIcon_1310_Ultra.png",
        "LevelUpSkillID": [
          131003
        ],
        "MaterialList": [
          {
            "$type": "ItemConfigRow",
            "ItemID": 2,
            "ItemNum": 2500
          },
          {
            "$type": "ItemConfigRow",
            "ItemID": 114011,
            "ItemNum": 3
          }
        ],
        "MaxLevel": 10,
        "ParamList": [],
        "PointID": 1310003,
        "PointName": null,
        "PointDesc": null,
        "PointTriggerKey": -747226677,
        "PointType": 2,
        "PrePoint": [],
        "StatusAddList": []
      },
      "3": {
        "Anchor": "Point03",
        "AvatarPromotionLimit": 2,
        "AvatarLevelLimit": null,
        "DefaultUnlock": false,
        "Icon": "SkillIcon_1310_Ultra.png",
        "LevelUpSkillID": [
          131003
        ],
        "MaterialList": [
          {
            "$type": "ItemConfigRow",
            "ItemID": 2,
            "ItemNum": 5000
          },
          {
            "$type": "ItemConfigRow",
            "ItemID": 110181,
            "ItemNum": 3
          },
          {
            "$type": "ItemConfigRow",
            "ItemID": 114011,
            "ItemNum": 6
          }
        ],
        "MaxLevel": 10,
        "ParamList": [],
        "PointID": 1310003,
        "PointName": null,
        "PointDesc": null,
        "PointTriggerKey": -747226677,
        "PointType": 2,
        "PrePoint": [],
        "StatusAddList": []
      },
      "4": {
        "Anchor": "Point03",
        "AvatarPromotionLimit": 3,
        "AvatarLevelLimit": null,
        "DefaultUnlock": false,
        "Icon": "SkillIcon_1310_Ultra.png",
        "LevelUpSkillID": [
          131003
        ],
        "MaterialList": [
          {
            "$type": "ItemConfigRow",
            "ItemID": 2,
            "ItemNum": 10000
          },
          {
            "$type": "ItemConfigRow",
            "ItemID": 110182,
            "ItemNum": 3
          },
          {
            "$type": "ItemConfigRow",
            "ItemID": 114012,
            "ItemNum": 3
          }
        ],
        "MaxLevel": 10,
        "ParamList": [],
        "PointID": 1310003,
        "PointName": null,
        "PointDesc": null,
        "PointTriggerKey": -747226677,
        "PointType": 2,
        "PrePoint": [],
        "StatusAddList": []
      },
      "5": {
        "Anchor": "Point03",
        "AvatarPromotionLimit": 4,
        "AvatarLevelLimit": null,
        "DefaultUnlock": false,
        "Icon": "SkillIcon_1310_Ultra.png",
        "LevelUpSkillID": [
          131003
        ],
        "MaterialList": [
          {
            "$type": "ItemConfigRow",
            "ItemID": 2,
            "ItemNum": 20000
          },
          {
            "$type": "ItemConfigRow",
            "ItemID": 110182,
            "ItemNum": 5
          },
          {
            "$type": "ItemConfigRow",
            "ItemID": 114012,
            "ItemNum": 4
          }
        ],
        "MaxLevel": 10,
        "ParamList": [],
        "PointID": 1310003,
        "PointName": null,
        "PointDesc": null,
        "PointTriggerKey": -747226677,
        "PointType": 2,
        "PrePoint": [],
        "StatusAddList": []
      },
      "6": {
        "Anchor": "Point03",
        "AvatarPromotionLimit": 4,
        "AvatarLevelLimit": null,
        "DefaultUnlock": false,
        "Icon": "SkillIcon_1310_Ultra.png",
        "LevelUpSkillID": [
          131003
        ],
        "MaterialList": [
          {
            "$type": "ItemConfigRow",
            "ItemID": 2,
            "ItemNum": 30000
          },
          {
            "$type": "ItemConfigRow",
            "ItemID": 110182,
            "ItemNum": 7
          },
          {
            "$type": "ItemConfigRow",
            "ItemID": 114012,
            "ItemNum": 6
          }
        ],
        "MaxLevel": 10,
        "ParamList": [],
        "PointID": 1310003,
        "PointName": null,
        "PointDesc": null,
        "PointTriggerKey": -747226677,
        "PointType": 2,
        "PrePoint": [],
        "StatusAddList": []
      },
      "7": {
        "Anchor": "Point03",
        "AvatarPromotionLimit": 5,
        "AvatarLevelLimit": null,
        "DefaultUnlock": false,
        "Icon": "SkillIcon_1310_Ultra.png",
        "LevelUpSkillID": [
          131003
        ],
        "MaterialList": [
          {
            "$type": "ItemConfigRow",
            "ItemID": 2,
            "ItemNum": 45000
          },
          {
            "$type": "ItemConfigRow",
            "ItemID": 110183,
            "ItemNum": 3
          },
          {
            "$type": "ItemConfigRow",
            "ItemID": 114013,
            "ItemNum": 3
          }
        ],
        "MaxLevel": 10,
        "ParamList": [],
        "PointID": 1310003,
        "PointName": null,
        "PointDesc": null,
        "PointTriggerKey": -747226677,
        "PointType": 2,
        "PrePoint": [],
        "StatusAddList": []
      },
      "8": {
        "Anchor": "Point03",
        "AvatarPromotionLimit": 5,
        "AvatarLevelLimit": null,
        "DefaultUnlock": false,
        "Icon": "SkillIcon_1310_Ultra.png",
        "LevelUpSkillID": [
          131003
        ],
        "MaterialList": [
          {
            "$type": "ItemConfigRow",
            "ItemID": 2,
            "ItemNum": 80000
          },
          {
            "$type": "ItemConfigRow",
            "ItemID": 110183,
            "ItemNum": 5
          },
          {
            "$type": "ItemConfigRow",
            "ItemID": 110505,
            "ItemNum": 1
          },
          {
            "$type": "ItemConfigRow",
            "ItemID": 114013,
            "ItemNum": 4
          }
        ],
        "MaxLevel": 10,
        "ParamList": [],
        "PointID": 1310003,
        "PointName": null,
        "PointDesc": null,
        "PointTriggerKey": -747226677,
        "PointType": 2,
        "PrePoint": [],
        "StatusAddList": []
      },
      "9": {
        "Anchor": "Point03",
        "AvatarPromotionLimit": 6,
        "AvatarLevelLimit": null,
        "DefaultUnlock": false,
        "Icon": "SkillIcon_1310_Ultra.png",
        "LevelUpSkillID": [
          131003
        ],
        "MaterialList": [
          {
            "$type": "ItemConfigRow",
            "ItemID": 2,
            "ItemNum": 160000
          },
          {
            "$type": "ItemConfigRow",
            "ItemID": 110183,
            "ItemNum": 8
          },
          {
            "$type": "ItemConfigRow",
            "ItemID": 241,
            "ItemNum": 1
          },
          {
            "$type": "ItemConfigRow",
            "ItemID": 110505,
            "ItemNum": 1
          }
        ],
        "MaxLevel": 10,
        "ParamList": [],
        "PointID": 1310003,
        "PointName": null,
        "PointDesc": null,
        "PointTriggerKey": -747226677,
        "PointType": 2,
        "PrePoint": [],
        "StatusAddList": []
      },
      "10": {
        "Anchor": "Point03",
        "AvatarPromotionLimit": 6,
        "AvatarLevelLimit": null,
        "DefaultUnlock": false,
        "Icon": "SkillIcon_1310_Ultra.png",
        "LevelUpSkillID": [
          131003
        ],
        "MaterialList": [
          {
            "$type": "ItemConfigRow",
            "ItemID": 2,
            "ItemNum": 300000
          },
          {
            "$type": "ItemConfigRow",
            "ItemID": 110183,
            "ItemNum": 14
          },
          {
            "$type": "ItemConfigRow",
            "ItemID": 241,
            "ItemNum": 1
          },
          {
            "$type": "ItemConfigRow",
            "ItemID": 110505,
            "ItemNum": 1
          }
        ],
        "MaxLevel": 10,
        "ParamList": [],
        "PointID": 1310003,
        "PointName": null,
        "PointDesc": null,
        "PointTriggerKey": -747226677,
        "PointType": 2,
        "PrePoint": [],
        "StatusAddList": []
      }
    },
    "Point04": {
      "1": {
        "Anchor": "Point04",
        "AvatarPromotionLimit": null,
        "AvatarLevelLimit": null,
        "DefaultUnlock": true,
        "Icon": "SkillIcon_1310_Passive.png",
        "LevelUpSkillID": [
          131004
        ],
        "MaterialList": [],
        "MaxLevel": 10,
        "ParamList": [],
        "PointID": 1310004,
        "PointName": null,
        "PointDesc": null,
        "PointTriggerKey": 1042505347,
        "PointType": 2,
        "PrePoint": [],
        "StatusAddList": []
      },
      "2": {
        "Anchor": "Point04",
        "AvatarPromotionLimit": 1,
        "AvatarLevelLimit": null,
        "DefaultUnlock": false,
        "Icon": "SkillIcon_1310_Passive.png",
        "LevelUpSkillID": [
          131004
        ],
        "MaterialList": [
          {
            "$type": "ItemConfigRow",
            "ItemID": 2,
            "ItemNum": 2500
          },
          {
            "$type": "ItemConfigRow",
            "ItemID": 114011,
            "ItemNum": 3
          }
        ],
        "MaxLevel": 10,
        "ParamList": [],
        "PointID": 1310004,
        "PointName": null,
        "PointDesc": null,
        "PointTriggerKey": 1042505347,
        "PointType": 2,
        "PrePoint": [],
        "StatusAddList": []
      },
      "3": {
        "Anchor": "Point04",
        "AvatarPromotionLimit": 2,
        "AvatarLevelLimit": null,
        "DefaultUnlock": false,
        "Icon": "SkillIcon_1310_Passive.png",
        "LevelUpSkillID": [
          131004
        ],
        "MaterialList": [
          {
            "$type": "ItemConfigRow",
            "ItemID": 2,
            "ItemNum": 5000
          },
          {
            "$type": "ItemConfigRow",
            "ItemID": 110181,
            "ItemNum": 3
          },
          {
            "$type": "ItemConfigRow",
            "ItemID": 114011,
            "ItemNum": 6
          }
        ],
        "MaxLevel": 10,
        "ParamList": [],
        "PointID": 1310004,
        "PointName": null,
        "PointDesc": null,
        "PointTriggerKey": 1042505347,
        "PointType": 2,
        "PrePoint": [],
        "StatusAddList": []
      },
      "4": {
        "Anchor": "Point04",
        "AvatarPromotionLimit": 3,
        "AvatarLevelLimit": null,
        "DefaultUnlock": false,
        "Icon": "SkillIcon_1310_Passive.png",
        "LevelUpSkillID": [
          131004
        ],
        "MaterialList": [
          {
            "$type": "ItemConfigRow",
            "ItemID": 2,
            "ItemNum": 10000
          },
          {
            "$type": "ItemConfigRow",
            "ItemID": 110182,
            "ItemNum": 3
          },
          {
            "$type": "ItemConfigRow",
            "ItemID": 114012,
            "ItemNum": 3
          }
        ],
        "MaxLevel": 10,
        "ParamList": [],
        "PointID": 1310004,
        "PointName": null,
        "PointDesc": null,
        "PointTriggerKey": 1042505347,
        "PointType": 2,
        "PrePoint": [],
        "StatusAddList": []
      },
      "5": {
        "Anchor": "Point04",
        "AvatarPromotionLimit": 4,
        "AvatarLevelLimit": null,
        "DefaultUnlock": false,
        "Icon": "SkillIcon_1310_Passive.png",
        "LevelUpSkillID": [
          131004
        ],
        "MaterialList": [
          {
            "$type": "ItemConfigRow",
            "ItemID": 2,
            "ItemNum": 20000
          },
          {
            "$type": "ItemConfigRow",
            "ItemID": 110182,
            "ItemNum": 5
          },
          {
            "$type": "ItemConfigRow",
            "ItemID": 114012,
            "ItemNum": 4
          }
        ],
        "MaxLevel": 10,
        "ParamList": [],
        "PointID": 1310004,
        "PointName": null,
        "PointDesc": null,
        "PointTriggerKey": 1042505347,
        "PointType": 2,
        "PrePoint": [],
        "StatusAddList": []
      },
      "6": {
        "Anchor": "Point04",
        "AvatarPromotionLimit": 4,
        "AvatarLevelLimit": null,
        "DefaultUnlock": false,
        "Icon": "SkillIcon_1310_Passive.png",
        "LevelUpSkillID": [
          131004
        ],
        "MaterialList": [
          {
            "$type": "ItemConfigRow",
            "ItemID": 2,
            "ItemNum": 30000
          },
          {
            "$type": "ItemConfigRow",
            "ItemID": 110182,
            "ItemNum": 7
          },
          {
            "$type": "ItemConfigRow",
            "ItemID": 114012,
            "ItemNum": 6
          }
        ],
        "MaxLevel": 10,
        "ParamList": [],
        "PointID": 1310004,
        "PointName": null,
        "PointDesc": null,
        "PointTriggerKey": 1042505347,
        "PointType": 2,
        "PrePoint": [],
        "StatusAddList": []
      },
      "7": {
        "Anchor": "Point04",
        "AvatarPromotionLimit": 5,
        "AvatarLevelLimit": null,
        "DefaultUnlock": false,
        "Icon": "SkillIcon_1310_Passive.png",
        "LevelUpSkillID": [
          131004
        ],
        "MaterialList": [
          {
            "$type": "ItemConfigRow",
            "ItemID": 2,
            "ItemNum": 45000
          },
          {
            "$type": "ItemConfigRow",
            "ItemID": 110183,
            "ItemNum": 3
          },
          {
            "$type": "ItemConfigRow",
            "ItemID": 114013,
            "ItemNum": 3
          }
        ],
        "MaxLevel": 10,
        "ParamList": [],
        "PointID": 1310004,
        "PointName": null,
        "PointDesc": null,
        "PointTriggerKey": 1042505347,
        "PointType": 2,
        "PrePoint": [],
        "StatusAddList": []
      },
      "8": {
        "Anchor": "Point04",
        "AvatarPromotionLimit": 5,
        "AvatarLevelLimit": null,
        "DefaultUnlock": false,
        "Icon": "SkillIcon_1310_Passive.png",
        "LevelUpSkillID": [
          131004
        ],
        "MaterialList": [
          {
            "$type": "ItemConfigRow",
            "ItemID": 2,
            "ItemNum": 80000
          },
          {
            "$type": "ItemConfigRow",
            "ItemID": 110183,
            "ItemNum": 5
          },
          {
            "$type": "ItemConfigRow",
            "ItemID": 110505,
            "ItemNum": 1
          },
          {
            "$type": "ItemConfigRow",
            "ItemID": 114013,
            "ItemNum": 4
          }
        ],
        "MaxLevel": 10,
        "ParamList": [],
        "PointID": 1310004,
        "PointName": null,
        "PointDesc": null,
        "PointTriggerKey": 1042505347,
        "PointType": 2,
        "PrePoint": [],
        "StatusAddList": []
      },
      "9": {
        "Anchor": "Point04",
        "AvatarPromotionLimit": 6,
        "AvatarLevelLimit": null,
        "DefaultUnlock": false,
        "Icon": "SkillIcon_1310_Passive.png",
        "LevelUpSkillID": [
          131004
        ],
        "MaterialList": [
          {
            "$type": "ItemConfigRow",
            "ItemID": 2,
            "ItemNum": 160000
          },
          {
            "$type": "ItemConfigRow",
            "ItemID": 110183,
            "ItemNum": 8
          },
          {
            "$type": "ItemConfigRow",
            "ItemID": 241,
            "ItemNum": 1
          },
          {
            "$type": "ItemConfigRow",
            "ItemID": 110505,
            "ItemNum": 1
          }
        ],
        "MaxLevel": 10,
        "ParamList": [],
        "PointID": 1310004,
        "PointName": null,
        "PointDesc": null,
        "PointTriggerKey": 1042505347,
        "PointType": 2,
        "PrePoint": [],
        "StatusAddList": []
      },
      "10": {
        "Anchor": "Point04",
        "AvatarPromotionLimit": 6,
        "AvatarLevelLimit": null,
        "DefaultUnlock": false,
        "Icon": "SkillIcon_1310_Passive.png",
        "LevelUpSkillID": [
          131004
        ],
        "MaterialList": [
          {
            "$type": "ItemConfigRow",
            "ItemID": 2,
            "ItemNum": 300000
          },
          {
            "$type": "ItemConfigRow",
            "ItemID": 110183,
            "ItemNum": 14
          },
          {
            "$type": "ItemConfigRow",
            "ItemID": 241,
            "ItemNum": 1
          },
          {
            "$type": "ItemConfigRow",
            "ItemID": 110505,
            "ItemNum": 1
          }
        ],
        "MaxLevel": 10,
        "ParamList": [],
        "PointID": 1310004,
        "PointName": null,
        "PointDesc": null,
        "PointTriggerKey": 1042505347,
        "PointType": 2,
        "PrePoint": [],
        "StatusAddList": []
      }
    },
    "Point05": {
      "1": {
        "Anchor": "Point05",
        "AvatarPromotionLimit": null,
        "AvatarLevelLimit": null,
        "DefaultUnlock": true,
        "Icon": "SkillIcon_1310_Maze.png",
        "LevelUpSkillID": [
          131007
        ],
        "MaterialList": [],
        "MaxLevel": 1,
        "ParamList": [],
        "PointID": 1310007,
        "PointName": null,
        "PointDesc": null,
        "PointTriggerKey": 1124256395,
        "PointType": 2,
        "PrePoint": [],
        "StatusAddList": []
      }
    },
    "Point06": {
      "1": {
        "Anchor": "Point06",
        "AvatarPromotionLimit": 2,
        "AvatarLevelLimit": null,
        "DefaultUnlock": false,
        "Icon": "SkillIcon_1310_SkillTree1.png",
        "LevelUpSkillID": [],
        "MaterialList": [
          {
            "$type": "ItemConfigRow",
            "ItemID": 2,
            "ItemNum": 5000
          },
          {
            "$type": "ItemConfigRow",
            "ItemID": 110181,
            "ItemNum": 3
          },
          {
            "$type": "ItemConfigRow",
            "ItemID": 110505,
            "ItemNum": 1
          }
        ],
        "MaxLevel": 1,
        "ParamList": [
          0.5500000005122274
        ],
        "PointID": 1310101,
        "PointName": "Module α: Antilag Outburst",
        "PointDesc": "While in Complete Combustion, attacking enemies without Fire Weakness can also reduce Toughness by an amount equal to <unbreak>#1[i]%</unbreak> of the original ability's Toughness Reduction.",
        "PointTriggerKey": 1455742903,
        "PointType": 3,
        "PrePoint": [],
        "StatusAddList": []
      }
    },
    "Point07": {
      "1": {
        "Anchor": "Point07",
        "AvatarPromotionLimit": 4,
        "AvatarLevelLimit": null,
        "DefaultUnlock": false,
        "Icon": "SkillIcon_1310_SkillTree2.png",
        "LevelUpSkillID": [],
        "MaterialList": [
          {
            "$type": "ItemConfigRow",
            "ItemID": 2,
            "ItemNum": 20000
          },
          {
            "$type": "ItemConfigRow",
            "ItemID": 110182,
            "ItemNum": 5
          },
          {
            "$type": "ItemConfigRow",
            "ItemID": 241,
            "ItemNum": 1
          },
          {
            "$type": "ItemConfigRow",
            "ItemID": 110505,
            "ItemNum": 1
          }
        ],
        "MaxLevel": 1,
        "ParamList": [
          2,
          3.6000000005587935,
          0.3500000003259629,
          0.5000000004656613
        ],
        "PointID": 1310102,
        "PointName": "Module β: Autoreactive Armor",
        "PointDesc": "Under Complete Combustion, when SAM's Break Effect is equal to or greater than <unbreak>#1[i]%</unbreak>/<unbreak>#2[i]%</unbreak>, attacking a Weakness-Broken enemy target will convert the Toughness Reduction of this attack into 1 instance of <unbreak>#3[i]%</unbreak>/<unbreak>#4[i]%</unbreak> Super Break DMG.",
        "PointTriggerKey": 1455742904,
        "PointType": 3,
        "PrePoint": [],
        "StatusAddList": []
      }
    },
    "Point08": {
      "1": {
        "Anchor": "Point08",
        "AvatarPromotionLimit": 6,
        "AvatarLevelLimit": null,
        "DefaultUnlock": false,
        "Icon": "SkillIcon_1310_SkillTree3.png",
        "LevelUpSkillID": [],
        "MaterialList": [
          {
            "$type": "ItemConfigRow",
            "ItemID": 2,
            "ItemNum": 160000
          },
          {
            "$type": "ItemConfigRow",
            "ItemID": 110183,
            "ItemNum": 8
          },
          {
            "$type": "ItemConfigRow",
            "ItemID": 241,
            "ItemNum": 1
          },
          {
            "$type": "ItemConfigRow",
            "ItemID": 110505,
            "ItemNum": 1
          }
        ],
        "MaxLevel": 1,
        "ParamList": [
          1600,
          100,
          0.10000000009313226
        ],
        "PointID": 1310103,
        "PointName": "Module γ: Core Overload",
        "PointDesc": "For every <unbreak>#2[i]</unbreak> of SAM's ATK that exceeds <unbreak>#1[i]</unbreak>, increases SAM's Break Effect by <unbreak>#3[i]%</unbreak>.",
        "PointTriggerKey": 1455742905,
        "PointType": 3,
        "PrePoint": [],
        "StatusAddList": []
      }
    },
    "Point09": {
      "1": {
        "Anchor": "Point09",
        "AvatarPromotionLimit": null,
        "AvatarLevelLimit": 1,
        "DefaultUnlock": false,
        "Icon": "IconBreakUp.png",
        "LevelUpSkillID": [],
        "MaterialList": [
          {
            "$type": "ItemConfigRow",
            "ItemID": 2,
            "ItemNum": 2500
          },
          {
            "$type": "ItemConfigRow",
            "ItemID": 114011,
            "ItemNum": 2
          }
        ],
        "MaxLevel": 1,
        "ParamList": [],
        "PointID": 1310201,
        "PointName": "Break Boost",
        "PointDesc": null,
        "PointTriggerKey": -1985601171,
        "PointType": 1,
        "PrePoint": [],
        "StatusAddList": [
          {
            "$type": "AvatarPropertyValue",
            "PropertyType": "BreakDamageAddedRatioBase",
            "Value": 0.05299999983981252
          }
        ]
      }
    },
    "Point10": {
      "1": {
        "Anchor": "Point10",
        "AvatarPromotionLimit": 2,
        "AvatarLevelLimit": null,
        "DefaultUnlock": false,
        "Icon": "IconStatusResistance.png",
        "LevelUpSkillID": [],
        "MaterialList": [
          {
            "$type": "ItemConfigRow",
            "ItemID": 2,
            "ItemNum": 5000
          },
          {
            "$type": "ItemConfigRow",
            "ItemID": 110181,
            "ItemNum": 3
          },
          {
            "$type": "ItemConfigRow",
            "ItemID": 114011,
            "ItemNum": 6
          }
        ],
        "MaxLevel": 1,
        "ParamList": [],
        "PointID": 1310202,
        "PointName": "Effect RES Boost",
        "PointDesc": null,
        "PointTriggerKey": -1985601170,
        "PointType": 1,
        "PrePoint": [
          1310101
        ],
        "StatusAddList": [
          {
            "$type": "AvatarPropertyValue",
            "PropertyType": "StatusResistanceBase",
            "Value": 0.0400000000372529
          }
        ]
      }
    },
    "Point11": {
      "1": {
        "Anchor": "Point11",
        "AvatarPromotionLimit": 3,
        "AvatarLevelLimit": null,
        "DefaultUnlock": false,
        "Icon": "IconBreakUp.png",
        "LevelUpSkillID": [],
        "MaterialList": [
          {
            "$type": "ItemConfigRow",
            "ItemID": 2,
            "ItemNum": 10000
          },
          {
            "$type": "ItemConfigRow",
            "ItemID": 110182,
            "ItemNum": 3
          },
          {
            "$type": "ItemConfigRow",
            "ItemID": 114012,
            "ItemNum": 3
          }
        ],
        "MaxLevel": 1,
        "ParamList": [],
        "PointID": 1310203,
        "PointName": "Break Boost",
        "PointDesc": null,
        "PointTriggerKey": -1985601169,
        "PointType": 1,
        "PrePoint": [
          1310202
        ],
        "StatusAddList": [
          {
            "$type": "AvatarPropertyValue",
            "PropertyType": "BreakDamageAddedRatioBase",
            "Value": 0.05299999983981252
          }
        ]
      }
    },
    "Point12": {
      "1": {
        "Anchor": "Point12",
        "AvatarPromotionLimit": 3,
        "AvatarLevelLimit": null,
        "DefaultUnlock": false,
        "Icon": "IconSpeed.png",
        "LevelUpSkillID": [],
        "MaterialList": [
          {
            "$type": "ItemConfigRow",
            "ItemID": 2,
            "ItemNum": 10000
          },
          {
            "$type": "ItemConfigRow",
            "ItemID": 110182,
            "ItemNum": 3
          },
          {
            "$type": "ItemConfigRow",
            "ItemID": 114012,
            "ItemNum": 3
          }
        ],
        "MaxLevel": 1,
        "ParamList": [],
        "PointID": 1310204,
        "PointName": "SPD Boost",
        "PointDesc": null,
        "PointTriggerKey": -1985601168,
        "PointType": 1,
        "PrePoint": [
          1310203
        ],
        "StatusAddList": [
          {
            "$type": "AvatarPropertyValue",
            "PropertyType": "SpeedDelta",
            "Value": 2
          }
        ]
      }
    },
    "Point13": {
      "1": {
        "Anchor": "Point13",
        "AvatarPromotionLimit": 4,
        "AvatarLevelLimit": null,
        "DefaultUnlock": false,
        "Icon": "IconBreakUp.png",
        "LevelUpSkillID": [],
        "MaterialList": [
          {
            "$type": "ItemConfigRow",
            "ItemID": 2,
            "ItemNum": 20000
          },
          {
            "$type": "ItemConfigRow",
            "ItemID": 110182,
            "ItemNum": 5
          },
          {
            "$type": "ItemConfigRow",
            "ItemID": 114012,
            "ItemNum": 4
          }
        ],
        "MaxLevel": 1,
        "ParamList": [],
        "PointID": 1310205,
        "PointName": "Break Boost",
        "PointDesc": null,
        "PointTriggerKey": -1985601167,
        "PointType": 1,
        "PrePoint": [
          1310102
        ],
        "StatusAddList": [
          {
            "$type": "AvatarPropertyValue",
            "PropertyType": "BreakDamageAddedRatioBase",
            "Value": 0.0800000000745058
          }
        ]
      }
    },
    "Point14": {
      "1": {
        "Anchor": "Point14",
        "AvatarPromotionLimit": 5,
        "AvatarLevelLimit": null,
        "DefaultUnlock": false,
        "Icon": "IconStatusResistance.png",
        "LevelUpSkillID": [],
        "MaterialList": [
          {
            "$type": "ItemConfigRow",
            "ItemID": 2,
            "ItemNum": 45000
          },
          {
            "$type": "ItemConfigRow",
            "ItemID": 110183,
            "ItemNum": 3
          },
          {
            "$type": "ItemConfigRow",
            "ItemID": 114013,
            "ItemNum": 3
          }
        ],
        "MaxLevel": 1,
        "ParamList": [],
        "PointID": 1310206,
        "PointName": "Effect RES Boost",
        "PointDesc": null,
        "PointTriggerKey": -1985601166,
        "PointType": 1,
        "PrePoint": [
          1310205
        ],
        "StatusAddList": [
          {
            "$type": "AvatarPropertyValue",
            "PropertyType": "StatusResistanceBase",
            "Value": 0.060000000055879354
          }
        ]
      }
    },
    "Point15": {
      "1": {
        "Anchor": "Point15",
        "AvatarPromotionLimit": 5,
        "AvatarLevelLimit": null,
        "DefaultUnlock": false,
        "Icon": "IconBreakUp.png",
        "LevelUpSkillID": [],
        "MaterialList": [
          {
            "$type": "ItemConfigRow",
            "ItemID": 2,
            "ItemNum": 45000
          },
          {
            "$type": "ItemConfigRow",
            "ItemID": 110183,
            "ItemNum": 3
          },
          {
            "$type": "ItemConfigRow",
            "ItemID": 114013,
            "ItemNum": 3
          }
        ],
        "MaxLevel": 1,
        "ParamList": [],
        "PointID": 1310207,
        "PointName": "Break Boost",
        "PointDesc": null,
        "PointTriggerKey": -1985601165,
        "PointType": 1,
        "PrePoint": [
          1310206
        ],
        "StatusAddList": [
          {
            "$type": "AvatarPropertyValue",
            "PropertyType": "BreakDamageAddedRatioBase",
            "Value": 0.0800000000745058
          }
        ]
      }
    },
    "Point16": {
      "1": {
        "Anchor": "Point16",
        "AvatarPromotionLimit": 6,
        "AvatarLevelLimit": null,
        "DefaultUnlock": false,
        "Icon": "IconSpeed.png",
        "LevelUpSkillID": [],
        "MaterialList": [
          {
            "$type": "ItemConfigRow",
            "ItemID": 2,
            "ItemNum": 160000
          },
          {
            "$type": "ItemConfigRow",
            "ItemID": 110183,
            "ItemNum": 8
          },
          {
            "$type": "ItemConfigRow",
            "ItemID": 114013,
            "ItemNum": 8
          }
        ],
        "MaxLevel": 1,
        "ParamList": [],
        "PointID": 1310208,
        "PointName": "SPD Boost",
        "PointDesc": null,
        "PointTriggerKey": -1985601180,
        "PointType": 1,
        "PrePoint": [
          1310103
        ],
        "StatusAddList": [
          {
            "$type": "AvatarPropertyValue",
            "PropertyType": "SpeedDelta",
            "Value": 3
          }
        ]
      }
    },
    "Point17": {
      "1": {
        "Anchor": "Point17",
        "AvatarPromotionLimit": null,
        "AvatarLevelLimit": 75,
        "DefaultUnlock": false,
        "Icon": "IconStatusResistance.png",
        "LevelUpSkillID": [],
        "MaterialList": [
          {
            "$type": "ItemConfigRow",
            "ItemID": 2,
            "ItemNum": 160000
          },
          {
            "$type": "ItemConfigRow",
            "ItemID": 110183,
            "ItemNum": 8
          },
          {
            "$type": "ItemConfigRow",
            "ItemID": 114013,
            "ItemNum": 8
          }
        ],
        "MaxLevel": 1,
        "ParamList": [],
        "PointID": 1310209,
        "PointName": "Effect RES Boost",
        "PointDesc": null,
        "PointTriggerKey": -1985601179,
        "PointType": 1,
        "PrePoint": [
          1310208
        ],
        "StatusAddList": [
          {
            "$type": "AvatarPropertyValue",
            "PropertyType": "StatusResistanceBase",
            "Value": 0.0800000000745058
          }
        ]
      }
    },
    "Point18": {
      "1": {
        "Anchor": "Point18",
        "AvatarPromotionLimit": null,
        "AvatarLevelLimit": 80,
        "DefaultUnlock": false,
        "Icon": "IconBreakUp.png",
        "LevelUpSkillID": [],
        "MaterialList": [
          {
            "$type": "ItemConfigRow",
            "ItemID": 2,
            "ItemNum": 160000
          },
          {
            "$type": "ItemConfigRow",
            "ItemID": 110183,
            "ItemNum": 8
          },
          {
            "$type": "ItemConfigRow",
            "ItemID": 114013,
            "ItemNum": 8
          }
        ],
        "MaxLevel": 1,
        "ParamList": [],
        "PointID": 1310210,
        "PointName": "Break Boost",
        "PointDesc": null,
        "PointTriggerKey": 44064284,
        "PointType": 1,
        "PrePoint": [
          1310208
        ],
        "StatusAddList": [
          {
            "$type": "AvatarPropertyValue",
            "PropertyType": "BreakDamageAddedRatioBase",
            "Value": 0.10699999961070716
          }
        ]
      }
    }
  },
  "Stats": {
    "0": {
      "AttackBase": 71.28000000026077,
      "AttackAdd": 3.564000000245869,
      "DefenceBase": 105.6000000005588,
      "DefenceAdd": 5.28000000026077,
      "HPBase": 110.88000000081956,
      "HPAdd": 5.544000000227243,
      "SpeedBase": 104,
      "CriticalChance": 0.05000000004656613,
      "CriticalDamage": 0.5000000004656613,
      "BaseAggro": 125,
      "Cost": [
        {
          "$type": "ItemConfigRow",
          "ItemID": 2,
          "ItemNum": 4000
        },
        {
          "$type": "ItemConfigRow",
          "ItemID": 114011,
          "ItemNum": 5
        }
      ]
    },
    "1": {
      "AttackBase": 99.79200000059791,
      "AttackAdd": 3.564000000245869,
      "DefenceBase": 147.8400000007823,
      "DefenceAdd": 5.28000000026077,
      "HPBase": 155.23200000007637,
      "HPAdd": 5.544000000227243,
      "SpeedBase": 104,
      "CriticalChance": 0.05000000004656613,
      "CriticalDamage": 0.5000000004656613,
      "BaseAggro": 125,
      "Cost": [
        {
          "$type": "ItemConfigRow",
          "ItemID": 2,
          "ItemNum": 8000
        },
        {
          "$type": "ItemConfigRow",
          "ItemID": 114011,
          "ItemNum": 10
        }
      ]
    },
    "2": {
      "AttackBase": 128.30400000000373,
      "AttackAdd": 3.564000000245869,
      "DefenceBase": 190.0800000000745,
      "DefenceAdd": 5.28000000026077,
      "HPBase": 199.5840000002645,
      "HPAdd": 5.544000000227243,
      "SpeedBase": 104,
      "CriticalChance": 0.05000000004656613,
      "CriticalDamage": 0.5000000004656613,
      "BaseAggro": 125,
      "Cost": [
        {
          "$type": "ItemConfigRow",
          "ItemID": 2,
          "ItemNum": 16000
        },
        {
          "$type": "ItemConfigRow",
          "ItemID": 114012,
          "ItemNum": 6
        },
        {
          "$type": "ItemConfigRow",
          "ItemID": 110422,
          "ItemNum": 3
        }
      ]
    },
    "3": {
      "AttackBase": 156.81600000034086,
      "AttackAdd": 3.564000000245869,
      "DefenceBase": 232.32000000029802,
      "DefenceAdd": 5.28000000026077,
      "HPBase": 243.93600000045262,
      "HPAdd": 5.544000000227243,
      "SpeedBase": 104,
      "CriticalChance": 0.05000000004656613,
      "CriticalDamage": 0.5000000004656613,
      "BaseAggro": 125,
      "Cost": [
        {
          "$type": "ItemConfigRow",
          "ItemID": 2,
          "ItemNum": 40000
        },
        {
          "$type": "ItemConfigRow",
          "ItemID": 114012,
          "ItemNum": 9
        },
        {
          "$type": "ItemConfigRow",
          "ItemID": 110422,
          "ItemNum": 7
        }
      ]
    },
    "4": {
      "AttackBase": 185.32799999974668,
      "AttackAdd": 3.564000000245869,
      "DefenceBase": 274.56000000052154,
      "DefenceAdd": 5.28000000026077,
      "HPBase": 288.2879999997094,
      "HPAdd": 5.544000000227243,
      "SpeedBase": 104,
      "CriticalChance": 0.05000000004656613,
      "CriticalDamage": 0.5000000004656613,
      "BaseAggro": 125,
      "Cost": [
        {
          "$type": "ItemConfigRow",
          "ItemID": 2,
          "ItemNum": 80000
        },
        {
          "$type": "ItemConfigRow",
          "ItemID": 114013,
          "ItemNum": 6
        },
        {
          "$type": "ItemConfigRow",
          "ItemID": 110422,
          "ItemNum": 20
        }
      ]
    },
    "5": {
      "AttackBase": 213.8400000007823,
      "AttackAdd": 3.564000000245869,
      "DefenceBase": 316.80000000074506,
      "DefenceAdd": 5.28000000026077,
      "HPBase": 332.64000000059605,
      "HPAdd": 5.544000000227243,
      "SpeedBase": 104,
      "CriticalChance": 0.05000000004656613,
      "CriticalDamage": 0.5000000004656613,
      "BaseAggro": 125,
      "Cost": [
        {
          "$type": "ItemConfigRow",
          "ItemID": 2,
          "ItemNum": 160000
        },
        {
          "$type": "ItemConfigRow",
          "ItemID": 114013,
          "ItemNum": 9
        },
        {
          "$type": "ItemConfigRow",
          "ItemID": 110422,
          "ItemNum": 35
        }
      ]
    },
    "6": {
      "AttackBase": 242.35200000018813,
      "AttackAdd": 3.564000000245869,
      "DefenceBase": 359.04000000003725,
      "DefenceAdd": 5.28000000026077,
      "HPBase": 376.9920000007842,
      "HPAdd": 5.544000000227243,
      "SpeedBase": 104,
      "CriticalChance": 0.05000000004656613,
      "CriticalDamage": 0.5000000004656613,
      "BaseAggro": 125,
      "Cost": []
    }
  },
  "Relics": {
    "AvatarID": 1310,
    "Set4IDList": [
      119,
      107,
      108
    ],
    "Set2IDList": [
      316,
      307,
      309
    ],
    "PropertyList": [
      {
        "$type": "RelicRecommendProperty",
        "RelicType": "BODY",
        "PropertyType": "AttackAddedRatio"
      },
      {
        "$type": "RelicRecommendProperty",
        "RelicType": "FOOT",
        "PropertyType": "SpeedDelta"
      },
      {
        "$type": "RelicRecommendProperty",
        "RelicType": "NECK",
        "PropertyType": "AttackAddedRatio"
      },
      {
        "$type": "RelicRecommendProperty",
        "RelicType": "OBJECT",
        "PropertyType": "BreakDamageAddedRatioBase"
      }
    ]
  }
}